LICENSE
MANIFEST.in
README.md
setup.cfg
setup.py
couscous/__init__.py
couscous/__main__.py
couscous/cli.py
couscous/couscous.py
couscous.egg-info/PKG-INFO
couscous.egg-info/SOURCES.txt
couscous.egg-info/dependency_links.txt
couscous.egg-info/entry_points.txt
couscous.egg-info/requires.txt
couscous.egg-info/top_level.txt