Metadata-Version: 2.1
Name: couscous
Version: 0.0.1
Summary: Experimental specification enabler.
Home-page: https://github.com/sthagen/improved-couscous
Author: Stefan Hagen
Author-email: stefan@hagen.link
License: MIT
Keywords: specification actionable enhance development
Platform: UNKNOWN
Classifier: Development Status :: 3 - Alpha
Classifier: Intended Audience :: Developers
Classifier: Topic :: Software Development :: Build Tools
Classifier: License :: OSI Approved :: MIT License
Classifier: Programming Language :: Python :: 3
Classifier: Programming Language :: Python :: 3.8
Classifier: Programming Language :: Python :: 3.9
